{"description":"Hello\n","name":"Hello","data":[{"description":"","hash":3262192268,"name":"","plugs":[[3523296417],[4293542123]],"tags":["GodPVE"]},{"description":"","hash":3262192268,"name":"","plugs":[[3523296417,2846385770,3436462433],[4293542123,11612903,365154968]],"tags":["PVE"]},{"description":"","hash":1125217994,"name":"","plugs":[[3523296417],[1015611457]],"tags":["GodPVE"]},{"description":"","hash":1125217994,"name":"","plugs":[[3523296417,1556840489],[1015611457,691659142]],"tags":["PVE"]}]}